butterpy/__init__.py
butterpy/core.py
butterpy/distributions.py
butterpy/flutter.py
butterpy/version.py
butterpy/io/__init__.py
butterpy/io/fits.py
butterpy/io/pkl.py
butterpy/utils/__init__.py
butterpy/utils/activelat.py
butterpy/utils/animation.py
butterpy/utils/diffrot.py
butterpy/utils/joyslaw.py
butterpy/utils/normalization.py
butterpy/utils/plots.py
butterpy/utils/spotevol.py
deprecated/__init__.py
deprecated/constants.py
deprecated/deprecated.py
deprecated/regions.py
deprecated/spots.py
deprecated/tests.py
tests/__init__.py
tests/butterpy_test.py
tests/test_distributions.py
butterpy-1.0.0.dist-info/LICENSE
butterpy-1.0.0.dist-info/METADATA
butterpy-1.0.0.dist-info/WHEEL
butterpy-1.0.0.dist-info/top_level.txt
butterpy-1.0.0.dist-info/RECORD
