Metadata-Version: 2.1
Name: butterpy
Version: 1.0.0
Summary: Tools for simulating stellar rotational light curves using realistic spot evolution
Home-page: https://github.com/zclaytor/butterpy
Author: Zachary R. Claytor <zclaytor@hawaii.edu> and Miles Lucas <mdlucas@hawaii.edu>
License: MIT
Classifier: Programming Language :: Python :: 3
Classifier: License :: OSI Approved :: MIT License
Classifier: Operating System :: Unix
Classifier: Intended Audience :: Science/Research
Classifier: Topic :: Scientific/Engineering :: Astronomy
Requires-Python: ==3.*
License-File: LICENSE
